macrometa_target_mysql/__init__.py
macrometa_target_mysql/constants.py
macrometa_target_mysql/sinks.py
macrometa_target_mysql/target.py
macrometa_target_mysql/tests/__init__.py
macrometa_target_mysql/tests/data_files/array_data.singer
macrometa_target_mysql/tests/data_files/camelcase.singer
macrometa_target_mysql/tests/data_files/camelcase_complex_schema.singer
macrometa_target_mysql/tests/data_files/duplicate_records.singer
macrometa_target_mysql/tests/data_files/encoded_strings.singer
macrometa_target_mysql/tests/data_files/illegal_colnames.singer
macrometa_target_mysql/tests/data_files/integer_null_value.singer
macrometa_target_mysql/tests/data_files/invalid_schema.singer
macrometa_target_mysql/tests/data_files/large_int.singer
macrometa_target_mysql/tests/data_files/missing_value.singer
macrometa_target_mysql/tests/data_files/multiple_state_messages.singer
macrometa_target_mysql/tests/data_files/no_primary_keys.singer
macrometa_target_mysql/tests/data_files/no_primary_keys_append.singer
macrometa_target_mysql/tests/data_files/numerics.singer
macrometa_target_mysql/tests/data_files/optional_attributes.singer
macrometa_target_mysql/tests/data_files/record_before_schema.singer
macrometa_target_mysql/tests/data_files/record_missing_key_property.singer
macrometa_target_mysql/tests/data_files/record_missing_required_property.singer
macrometa_target_mysql/tests/data_files/schema_no_properties.singer
macrometa_target_mysql/tests/data_files/schema_updates.singer
macrometa_target_mysql/tests/data_files/special_chars_in_attributes.singer
macrometa_target_mysql/tests/data_files/string_null_value.singer
macrometa_target_mysql/tests/data_files/tap_aapl.singer
macrometa_target_mysql/tests/data_files/target_schema.singer
macrometa_target_mysql/tests/data_files/update_records.singer
macrometa_target_mysql/tests/data_files/user_location_data.singer
macrometa_target_mysql/tests/data_files/user_location_upsert_data.singer
macrometa_target_mysql/tests/test_core.py
macrometa_target_mysql-0.0.12.dist-info/entry_points.txt
macrometa_target_mysql-0.0.12.dist-info/LICENSE
macrometa_target_mysql-0.0.12.dist-info/WHEEL
macrometa_target_mysql-0.0.12.dist-info/METADATA
macrometa_target_mysql-0.0.12.dist-info/RECORD
