Metadata-Version: 2.1
Name: macrometa-target-mysql
Version: 0.0.12
Summary: A Meltano target for MySQL.
License: Apache 2.0
Keywords: ELT,Connectors,Workflows,Macrometa,GDN,MySQL,Target
Author: Macrometa
Author-email: info@macrometa.com
Requires-Python: >=3.8.1,<3.11
Classifier: License :: Other/Proprietary License
Classifier: Programming Language :: Python :: 3
Classifier: Programming Language :: Python :: 3.9
Classifier: Programming Language :: Python :: 3.10
Requires-Dist: c8connector (==0.0.32)
Requires-Dist: cryptography (>=41.0.2,<42.0.0)
Requires-Dist: prometheus-client (==0.16.0)
Requires-Dist: pymysql (>=1.1.0,<2.0.0)
Requires-Dist: requests (>=2.25.1,<3.0.0)
Requires-Dist: singer-sdk (>=0.30.0,<0.31.0)
